evolutionary_optimization/__init__.py
evolutionary_optimization/evolutionary_algorithm/__init__.py
evolutionary_optimization/evolutionary_algorithm/ea_data_model.py
evolutionary_optimization/evolutionary_algorithm/ea_utils.py
evolutionary_optimization/evolutionary_algorithm/evolution.py
evolutionary_optimization/evolutionary_algorithm/population.py
evolutionary_optimization/fitness_functions/__init__.py
evolutionary_optimization/fitness_functions/abstract_fitness_function.py
evolutionary_optimization/fitness_functions/fitness_interface.py
evolutionary_optimization/fitness_functions/implemented_fitness_functions.py
evolutionary_optimization/genotype/__init__.py
evolutionary_optimization/genotype/genotype_model/__init__.py
evolutionary_optimization/genotype/genotype_model/abstract_genotype.py
evolutionary_optimization/genotype/genotype_model/genotype_interface.py
evolutionary_optimization/genotype/genotype_model/genotype_utils.py
evolutionary_optimization/genotype/implemented_genotypes/__init__.py
evolutionary_optimization/genotype/implemented_genotypes/binary_list_genotype.py
evolutionary_optimization/genotype/implemented_genotypes/float_list_genotype.py
evolutionary_optimization/genotype/implemented_genotypes/integer_list_genotype.py
evolutionary_optimization/main.py
evolutionary_optimization/phenotype/__init__.py
evolutionary_optimization/phenotype/implemented_phenotypes/__init__.py
evolutionary_optimization/phenotype/implemented_phenotypes/booth_phenotype.py
evolutionary_optimization/phenotype/implemented_phenotypes/inverted_parabola_phenotype.py
evolutionary_optimization/phenotype/implemented_phenotypes/parabola_phenotype.py
evolutionary_optimization/phenotype/implemented_phenotypes/saddle_point_phenotype.py
evolutionary_optimization/phenotype/phenotype_model/__init__.py
evolutionary_optimization/phenotype/phenotype_model/abstract_phenotype.py
evolutionary_optimization/phenotype/phenotype_model/phenotype_interface.py
evolutionary_optimization_algorithm-3.0.5.dist-info/entry_points.txt
evolutionary_optimization_algorithm-3.0.5.dist-info/WHEEL
evolutionary_optimization_algorithm-3.0.5.dist-info/METADATA
evolutionary_optimization_algorithm-3.0.5.dist-info/RECORD
